{
  "word": "unacceptable",
  "partOfSpeech": "adjective",
  "pronunciations": {
    "uk": [
      {
        "pronunciation": "/ˌʌnəkˈseptəbl/",
        "audio": "u/unacceptable/unacceptable__gb_1.mp3",
        "region": "br"
      }
    ],
    "us": [
      {
        "pronunciation": "/ˌʌnəkˈseptəbl/",
        "audio": "u/unacceptable/unacceptable__us_1.mp3",
        "region": "n_am"
      }
    ]
  },
  "verbForms": null,
  "definitions": [
    {
      "definition": "so bad that you think it should not be allowed",
      "examples": [
        {
          "text": "Such behaviour is totally unacceptable in a civilized society."
        },
        {
          "text": "Noise from the factory has reached an unacceptable level."
        },
        {
          "text": "Most people would consider such risks wholly unacceptable."
        },
        {
          "text": "Such a solution would be quite unacceptable to the majority of people."
        },
        {
          "text": "The cost of these proposed changes makes them unacceptable."
        },
        {
          "text": "There is nothing inherently unacceptable in these proposals."
        },
        {
          "text": "Raising taxes now would be politically unacceptable."
        }
      ],
      "collocations": {
        "verbs": ["be", "prove", "seem"],
        "adverb": ["absolutely", "completely", "entirely"],
        "preposition": ["to"]
      }
    }
  ],
  "wordOrigin": null
}
