{
  "word": "permanently",
  "partOfSpeech": "adverb",
  "pronunciations": {
    "uk": [
      {
        "pronunciation": "/ˈpɜːmənəntli/",
        "audio": "p/permanently/permanently__gb_1.mp3",
        "region": "br"
      }
    ],
    "us": [
      {
        "pronunciation": "/ˈpɜːrmənəntli/",
        "audio": "p/permanently/permanently__us_1.mp3",
        "region": "n_am"
      }
    ]
  },
  "verbForms": null,
  "definitions": [
    {
      "definition": "in a way that lasts for a long time or for all time in the future; in a way that exists all the time",
      "examples": [
        {
          "text": "The stroke left his right side permanently damaged."
        },
        {
          "text": "She had decided to settle permanently in France."
        },
        {
          "text": "This door is kept permanently locked."
        }
      ]
    }
  ],
  "wordOrigin": null
}
