{
	"term": "farming",
	"partOfSpeech": "noun",
	"ox3000": true,
	"cefr": "a2",
	"definitions": [
		{
			"senseNumber": null,
			"definition": "the business of managing or working on a farm",
			"labels": "(North American English)",
			"examples": [
				{
					"text": "to take up farming"
				},
				{
					"text": "**organic farming**"
				},
				{
					"text": "sheep/fish/salmon farming"
				},
				{
					"text": "modern farming methods"
				},
				{
					"text": "a farming community"
				},
				{
					"text": "the British farming industry"
				},
				{
					"text": "They lived by fishing and by basic small-scale farming."
				},
				{
					"text": "a farming operation where sheep are raised"
				},
				{
					"text": "the decline of traditional family farming"
				}
			],
			"topics": ["Farming"],
			"collocations": {
				"adjective": ["small-scale", "family", "subsistence"],
				"verb + farming": ["be engaged in", "work in"],
				"farming + noun": ["community", "industry", "sector"]
			}
		}
	],
	"pronunciations": {
		"uk": [
			{
				"pronunciation": "/ˈfɑːmɪŋ/",
				"audio": "fa/farming/farming__gb_1.mp3"
			}
		],
		"us": [
			{
				"pronunciation": "/ˈfɑːrmɪŋ/",
				"audio": "fa/farming/farming__us_3.mp3"
			}
		]
	},
	"wordOrigin": null
}
