{
  "word": "everywhere",
  "partOfSpeech": "adverb, pronoun, conjunction",
  "ox3000": true,
  "pronunciations": {
    "uk": [
      {
        "pronunciation": "/ˈevriweə(r)/",
        "audio": "e/everywhere/everywhere__gb_1.mp3",
        "region": "br"
      }
    ],
    "us": [
      {
        "pronunciation": "/ˈevriwer/",
        "audio": "e/everywhere/everywhere__us_1.mp3",
        "region": "n_am"
      }
    ]
  },
  "verbForms": null,
  "definitions": [
    {
      "definition": "in, to or at every place; all places",
      "examples": [
        {
          "text": "I've looked everywhere."
        },
        {
          "text": "He follows me everywhere."
        },
        {
          "text": "We'll have to eat here—**everywhere else** is full."
        },
        {
          "text": "Everywhere we went was full of tourists."
        }
      ]
    }
  ],
  "wordOrigin": "Middle English: formerly also as two words."
}
