{
  "term": "jeopardize",
  "partOfSpeech": "verb",
  "verbForms": {
    "presentSimple": {
      "iYouWeThey": "jeopardize",
      "heSheIt": "jeopardizes"
    },
    "pastSimple": "jeopardized",
    "pastParticiple": "jeopardized",
    "ingForm": "jeopardizing"
  },
  "definitions": [
    {
      "senseNumber": null,
      "definition": "to risk harming or destroying something/somebody",
      "sensetop": "jeopardize something/somebody",
      "examples": [
        {
          "text": "He would never do anything to jeopardize his career."
        },
        {
          "text": "This scandal could seriously jeopardize her chances of being re-elected."
        }
      ],
      "synonyms": "endanger",
      "collocations": {
        "adverb": ["seriously", "severely", "potentially"]
      }
    }
  ],
  "pronunciations": {
    "uk": [
      {
        "pronunciation": "/ˈdʒepədaɪz/",
        "audio": "je/jeopardize/jeopardize__gb_1.mp3"
      },
      {
        "pronunciation": "/ˈdʒepədaɪzɪz/",
        "audio": "je/jeopardize/jeopardizes__gb_1.mp3"
      },
      {
        "pronunciation": "/ˈdʒepədaɪzd/",
        "audio": "je/jeopardize/jeopardized__gb_1.mp3"
      },
      {
        "pronunciation": "/ˈdʒepədaɪzɪŋ/",
        "audio": "je/jeopardize/jeopardizing__gb_1.mp3"
      }
    ],
    "us": [
      {
        "pronunciation": "/ˈdʒepərdaɪz/",
        "audio": "je/jeopardize/jeopardize__us_1.mp3"
      },
      {
        "pronunciation": "/ˈdʒepərdaɪzɪz/",
        "audio": "je/jeopardize/jeopardizes__us_1.mp3"
      },
      {
        "pronunciation": "/ˈdʒepərdaɪzd/",
        "audio": "je/jeopardize/jeopardized__us_1.mp3"
      },
      {
        "pronunciation": "/ˈdʒepərdaɪzɪŋ/",
        "audio": "je/jeopardize/jeopardizing__us_1.mp3"
      }
    ]
  },
  "wordOrigin": null
}
