{
  "word": "kneel",
  "partOfSpeech": "verb",
  "pronunciations": {
    "uk": [
      {
        "pronunciation": "/niːl/",
        "audio": "data/audio/k/kneel/kneel__gb_2.mp3",
        "region": "br"
      },
      {
        "pronunciation": "/niːlz/",
        "audio": "data/audio/k/kneel/kneels__gb_1.mp3",
        "region": "br"
      },
      {
        "pronunciation": "/nelt/",
        "audio": "data/audio/k/kneel/knelt__gb_3.mp3",
        "region": "br"
      },
      {
        "pronunciation": "/niːld/",
        "audio": "data/audio/k/kneel/kneeled__gb_2.mp3",
        "region": "br"
      },
      {
        "pronunciation": "/ˈniːlɪŋ/",
        "audio": "data/audio/k/kneel/kneeling__gb_1.mp3",
        "region": "br"
      }
    ],
    "us": [
      {
        "pronunciation": "/niːl/",
        "audio": "data/audio/k/kneel/kneel__us_1.mp3",
        "region": "n_am"
      },
      {
        "pronunciation": "/niːlz/",
        "audio": "data/audio/k/kneel/kneels__us_1.mp3",
        "region": "n_am"
      },
      {
        "pronunciation": "/nelt/",
        "audio": "data/audio/k/kneel/knelt__us_1.mp3",
        "region": "n_am"
      },
      {
        "pronunciation": "/niːld/",
        "audio": "data/audio/k/kneel/kneeled__us_2.mp3",
        "region": "n_am"
      },
      {
        "pronunciation": "/ˈniːlɪŋ/",
        "audio": "data/audio/k/kneel/kneeling__us_1.mp3",
        "region": "n_am"
      }
    ]
  },
  "verbForms": {
    "presentSimple": {
      "iYouWeThey": "kneel",
      "heSheIt": "kneels"
    },
    "pastSimple": "knelt",
    "pastParticiple": "knelt",
    "ingForm": "kneeling"
  },
  "definitions": [
    {
      "definition": "to be in or move into a position where your body is supported on your knee or knees",
      "sensetop": "kneel (down)",
      "examples": [
        {
          "text": "a kneeling figure"
        },
        {
          "text": "People sometimes kneel to pray."
        },
        {
          "text": "We knelt (down) on the ground to examine the tracks.",
          "contextForm": "kneel (down)"
        },
        {
          "text": "The people knelt down and prayed."
        },
        {
          "text": "We knelt on the floor."
        },
        {
          "text": "He knelt and prayed for guidance."
        }
      ]
    }
  ],
  "wordOrigin": "Old English cnēowlian, from cnēow, of Germanic origin (see knee)."
}
